localtunnel/__init__.py
localtunnel/__main__.py
localtunnel/_logging.py
localtunnel/client.py
localtunnel/exceptions.py
localtunnel/header_transformer.py
localtunnel/tunnel_manager.py
localtunnel/utils.py
localtunnel_py-0.1.1.dist-info/LICENSE
localtunnel_py-0.1.1.dist-info/METADATA
localtunnel_py-0.1.1.dist-info/WHEEL
localtunnel_py-0.1.1.dist-info/entry_points.txt
localtunnel_py-0.1.1.dist-info/top_level.txt
localtunnel_py-0.1.1.dist-info/RECORD
