Metadata-Version: 2.1
Name: localtunnel-py
Version: 0.1.1
Summary: Python port of the localtunnel.me Client | Expose localhost to the world!
Home-page: https://github.com/gweidart/localtunnel-py
Author: gweidart
Author-email: gweidart <btnewcomer@pm.me>
License: MIT License
Project-URL: Homepage, https://github.com/gweidart/localtunnel-py.git
Project-URL: Documentation, https://github.com/gweidart/localtunnel-py/README.md
Project-URL: Repository, https://github.com/gweidart/localtunnel-py.git
Project-URL: Issues, https://github.com/gweidart/localtunnel-py/issues
Project-URL: Changelog, https://github.com/gweidart/localtunnel-py/blob/master/CHANGELOG.md
Keywords: localtunnel,tunnel,proxy,local server,port forwarding,subdomain,networking,http proxy,python client,cli tool,remote access,webhooks,cloud proxy,dynamic DNS,ngrok alternative,localhost,secure tunnel,public URL,developer tools,devops,system administration,network utilities,web server,firewalls,python library,python proxy,port tunneling
Classifier: Development Status :: 4 - Beta
Classifier: Intended Audience :: Developers
Classifier: Intended Audience :: Information Technology
Classifier: Intended Audience :: System Administrators
Classifier: License :: OSI Approved :: MIT License
Classifier: Programming Language :: Python
Classifier: Programming Language :: Python :: 3
Classifier: Programming Language :: Python :: 3.10
Classifier: Programming Language :: Python :: 3.11
Classifier: Programming Language :: Python :: 3.12
Classifier: Programming Language :: Python :: 3.13
Classifier: Programming Language :: Python :: Implementation :: CPython
Classifier: Topic :: Internet
Classifier: Topic :: Internet :: WWW/HTTP
Classifier: Topic :: Internet :: Proxy Servers
Classifier: Topic :: Internet :: WWW/HTTP :: Dynamic Content
Classifier: Topic :: Software Development
Classifier: Topic :: Software Development :: Libraries
Classifier: Topic :: Software Development :: Libraries :: Python Modules
Classifier: Topic :: Software Development :: Build Tools
Classifier: Topic :: System :: Networking
Classifier: Topic :: System :: Networking :: Firewalls
Classifier: Topic :: Utilities
Classifier: Natural Language :: English
Classifier: Operating System :: OS Independent
Requires-Python: >=3.12
License-File: LICENSE
Requires-Dist: aiohttp>=3.11.2
Requires-Dist: asyncio>=3.4.3
Requires-Dist: nest-asyncio>=1.5.6
Requires-Dist: rich>=13.9.4
